sengbao_mle/__init__.py
sengbao_mle/cores/__init__.py
sengbao_mle/cores/minuit.py
sengbao_mle/cores/util.py
sengbao_mle/distributions/__init__.py
sengbao_mle/model/__init__.py
sengbao_mle/model/model.py
sengbao_mle/tests/__init__.py
sengbao_mle/variable/__init__.py
sengbao_mle/variable/variable.py
sengbao_mle-0.0.1.dist-info/LICENSE
sengbao_mle-0.0.1.dist-info/METADATA
sengbao_mle-0.0.1.dist-info/WHEEL
sengbao_mle-0.0.1.dist-info/top_level.txt
sengbao_mle-0.0.1.dist-info/RECORD
