Metadata-Version: 2.1
Name: sengbao-mle
Version: 0.0.1
Summary: 翻新的最大似然估计库 maximum likelihood estimation
Home-page: https://github.com/chen-001/sengbao_mle.git
Author: chenzongwei
Author-email: winterwinter999@163.com
License: MIT
Requires-Python: >=3
License-File: LICENSE
Requires-Dist: numpy
Requires-Dist: scipy
Requires-Dist: theano
Requires-Dist: iminuit
